purewords/__init__.py
purewords/__main__.py
purewords/preprocessing.py
purewords/configs/stopwords.txt
purewords/filter_collection/__init__.py
purewords/filter_collection/base_filter_collection.py
purewords/filter_collection/default_filter_collections.py
purewords/filters/__init__.py
purewords/filters/base_filter.py
purewords/filters/pattern_replace_filter.py
purewords/filters/recursive_replace_filter.py
purewords/filters/stopwords_filter.py
purewords/filters/word_replace_filter.py
purewords/tokenizer/__init__.py
purewords/tokenizer/base_tokenizer.py
purewords/tokenizer/dict.txt.big.txt
purewords/tokenizer/jieba_tokenizer.py
purewords/tokenizer/whitespace_tokenizer.py
purewords/tokenizer/yoctol_tokenizer.py
purewords-0.1.1.dist-info/METADATA
purewords-0.1.1.dist-info/RECORD
purewords-0.1.1.dist-info/WHEEL
purewords-0.1.1.dist-info/top_level.txt
test/__init__.py
test/test_preprocessing.py
test/test_purewords.py
test/filters/__init__.py
test/filters/test_abbreviation_filter.py
test/filters/test_angle_brackets_filter.py
test/filters/test_blank_filter.py
test/filters/test_number_filter.py
test/filters/test_pattern_replace_filter.py
test/filters/test_phone_filter.py
test/filters/test_recursive_replace_filter.py
test/filters/test_stopwords_filter.py
test/filters/test_time_filter.py
test/filters/test_title_filter.py
test/filters/test_url_filter.py
test/filters/test_word_replace_filter.py
test/tokenizer/__init__.py
test/tokenizer/test_jieba_tokenizer.py
test/tokenizer/test_whitespace_tokenizer.py
test/tokenizer/test_yoctol_tokenizer.py
