Metadata-Version: 2.1
Name: purewords
Version: 0.1.1
Summary: A NLP preprocessing package
Home-page: UNKNOWN
Author: EN, PLLiao
License: MIT
Platform: UNKNOWN
Classifier: Programming Language :: Python
Classifier: Programming Language :: Python :: 3.5
Classifier: Programming Language :: Python :: 3.6
Requires-Python: >=3.5
Requires-Dist: jieba (==0.39)
Requires-Dist: joblib (==0.12.2)
